MANIFEST.in
README.md
setup.py
fileupload/__init__.py
fileupload/admin.py
fileupload/apps.py
fileupload/models.py
fileupload/public.py
fileupload/urls.py
fileupload/views.py
fileupload/migrations/0001_initial.py
fileupload/migrations/0002_auto_20190924_2020.py
fileupload/migrations/0003_fileupload_hash.py
fileupload/migrations/0004_fileupload_status.py
fileupload/migrations/__init__.py
internal_fileupload_django.egg-info/PKG-INFO
internal_fileupload_django.egg-info/SOURCES.txt
internal_fileupload_django.egg-info/dependency_links.txt
internal_fileupload_django.egg-info/top_level.txt
tests/__init__.py
tests/test_settings.py
tests/tests.py
tests/urls.py